fulladder.v
module full_adder(
    input a,
    input b,
    input cin,
    output sum,
    output cout
);
    assign sum  = a ^ b ^ cin;
    assign cout = (a & b) | (b & cin) | (a & cin);

endmodule

fulladder_tb.v
module full_adder_tb;
    reg a, b, cin;
    wire sum, cout;

    full_adder uut (
        .a(a),
        .b(b),
        .cin(cin),
        .sum(sum),
        .cout(cout)
    );

    initial begin
        $dumpfile("fulladder.vcd");
        $dumpvars(0, full_adder_tb);

        // Test all 8 combinations
        a=0; b=0; cin=0; #10;
        a=0; b=0; cin=1; #10;
        a=0; b=1; cin=0; #10;
        a=0; b=1; cin=1; #10;
        a=1; b=0; cin=0; #10;
        a=1; b=0; cin=1; #10;
        a=1; b=1; cin=0; #10;
        a=1; b=1; cin=1; #10;

        $display("Simulation complete");
        $finish;
    end

    initial begin
        $monitor("Time=%0t | a=%b b=%b cin=%b | sum=%b cout=%b",
                  $time, a, b, cin, sum, cout);
    end

endmodule

fulladder.vcd
$date
	Sun Apr 05 21:58:35 2026
$end
$version
	Icarus Verilog
$end
$timescale
	1s
$end
$scope module full_adder_tb $end
$var wire 1 ! sum $end
$var wire 1 " cout $end
$var reg 1 # a $end
$var reg 1 $ b $end
$var reg 1 % cin $end
$scope module uut $end
$var wire 1 # a $end
$var wire 1 $ b $end
$var wire 1 % cin $end
$var wire 1 " cout $end
$var wire 1 ! sum $end
$upscope $end
$upscope $end
$enddefinitions $end
$comment Show the parameter values. $end
$dumpall
$end
#0
$dumpvars
0%
0$
0#
0"
0!
$end
#10
1!
1%
#20
0%
1$
#30
1"
0!
1%
#40
0"
1!
0%
0$
1#
#50
1"
0!
1%
#60
0%
1$
#70
1!
1%
